aliexpressapi/__init__.py
aliexpressapi/search.py
AliExpressAPI-1.0.0.dist-info/LICENSE
AliExpressAPI-1.0.0.dist-info/METADATA
AliExpressAPI-1.0.0.dist-info/WHEEL
AliExpressAPI-1.0.0.dist-info/top_level.txt
AliExpressAPI-1.0.0.dist-info/RECORD
