Metadata-Version: 2.1
Name: AliExpressAPI
Version: 1.0.0
Summary: Get AliExpress results in a very very detailed JSON
Home-page: https://github.com/mytja/AliExpressAPI
Author: mytja
License: UNKNOWN
Platform: UNKNOWN
Classifier: Programming Language :: Python :: 3
Classifier: License :: OSI Approved :: MIT License
Classifier: Operating System :: OS Independent
Requires-Python: >=3
Requires-Dist: requests
Requires-Dist: beautifulsoup4
